gg/__init__.py
gg/color.py
gg/entity.py
gg/fsm.py
gg/game.py
gg/input.py
gg/interfaces.py
gg/mixins.py
gg/scene.py
gg/screen.py
gg/sprite.py
gg/surface.py
gg/utils.py
gg/examples/__init__.py
gg/examples/bbr/__init__.py
gg/examples/bbr/alien.py
gg/examples/bbr/background.py
gg/examples/bbr/ball.py
gg/examples/bbr/bricks.py
gg/examples/bbr/bullet.py
gg/examples/bbr/game.py
gg/examples/bbr/level.py
gg/examples/bbr/main.py
gg/examples/bbr/paddle.py
gg/examples/bbr/powerup.py
gg/examples/bbr/splash_screen.py
gg/examples/bbr/sprites.py
gg_lib-0.0.2.dist-info/LICENSE
gg_lib-0.0.2.dist-info/METADATA
gg_lib-0.0.2.dist-info/WHEEL
gg_lib-0.0.2.dist-info/top_level.txt
gg_lib-0.0.2.dist-info/RECORD
