Metadata-Version: 2.1
Name: gg-lib
Version: 0.0.2
Summary: A framework for creating terminal based games in python
Home-page: https://github.com/abakfja/gg
Author: Kannav Mehta
Author-email: kmkannavkmehta@gmail.com
License: UNKNOWN
Project-URL: Bug Tracker, https://github.com/abakfja/gg/issues
Platform: UNKNOWN
Classifier: Programming Language :: Python :: 3
Classifier: License :: OSI Approved :: MIT License
Classifier: Operating System :: OS Independent
Requires-Python: >=3.8
License-File: LICENSE
